WGFMUpy/__init__.py
WGFMUpy/libs/visa64.dll
WGFMUpy/libs/visaConfMgr.dll
WGFMUpy/libs/visaUtilities.dll
WGFMUpy/libs/wgfmu.dll
wgfmupy-0.0.6.dist-info/licenses/LICENSE
wgfmupy-0.0.6.dist-info/METADATA
wgfmupy-0.0.6.dist-info/WHEEL
wgfmupy-0.0.6.dist-info/top_level.txt
wgfmupy-0.0.6.dist-info/RECORD
